sparkdq/__init__.py
sparkdq/exceptions.py
sparkdq/py.typed
sparkdq/checks/__init__.py
sparkdq/checks/aggregate/__init__.py
sparkdq/checks/aggregate/completeness_checks/__init__.py
sparkdq/checks/aggregate/completeness_checks/columns_are_complete_check.py
sparkdq/checks/aggregate/completeness_checks/completeness_ratio_check.py
sparkdq/checks/aggregate/count_checks/__init__.py
sparkdq/checks/aggregate/count_checks/count_between_check.py
sparkdq/checks/aggregate/count_checks/count_exact_check.py
sparkdq/checks/aggregate/count_checks/count_max_check.py
sparkdq/checks/aggregate/count_checks/count_min_check.py
sparkdq/checks/aggregate/freshness_checks/__init__.py
sparkdq/checks/aggregate/freshness_checks/freshness_check.py
sparkdq/checks/aggregate/integrity_checks/__init__.py
sparkdq/checks/aggregate/integrity_checks/foreign_key_check.py
sparkdq/checks/aggregate/schema_checks/__init__.py
sparkdq/checks/aggregate/schema_checks/column_presence_check.py
sparkdq/checks/aggregate/schema_checks/schema_check.py
sparkdq/checks/aggregate/uniqueness_checks/__init__.py
sparkdq/checks/aggregate/uniqueness_checks/distinct_ratio_check.py
sparkdq/checks/aggregate/uniqueness_checks/unique_ratio_check.py
sparkdq/checks/aggregate/uniqueness_checks/unique_rows_check.py
sparkdq/checks/row_level/__init__.py
sparkdq/checks/row_level/columns_comparison_checks/__init__.py
sparkdq/checks/row_level/columns_comparison_checks/column_greater_than.py
sparkdq/checks/row_level/columns_comparison_checks/column_less_than.py
sparkdq/checks/row_level/contained_checks/__init__.py
sparkdq/checks/row_level/contained_checks/is_contained_in_check.py
sparkdq/checks/row_level/contained_checks/is_not_contained_in_check.py
sparkdq/checks/row_level/date_checks/__init__.py
sparkdq/checks/row_level/date_checks/date_between_check.py
sparkdq/checks/row_level/date_checks/date_max_check.py
sparkdq/checks/row_level/date_checks/date_min_check.py
sparkdq/checks/row_level/null_checks/__init__.py
sparkdq-0.11.0.dist-info/METADATA
sparkdq-0.11.0.dist-info/WHEEL
sparkdq-0.11.0.dist-info/licenses/LICENSE
sparkdq-0.11.0.dist-info/RECORD
