Metadata-Version: 2.4
Name: sparkdq
Version: 0.11.0
Summary: A declarative PySpark framework for row- and aggregate-level data quality validation.
Project-URL: homepage, https://github.com/sparkdq-community/sparkdq
Project-URL: documentation, https://sparkdq-community.github.io/sparkdq/
Author-email: Marcel Kennert <marcel.kennert@gmx.de>
License:                                  Apache License
License-File: LICENSE
Keywords: apache-spark,data-pipeline,data-quality,data-validation,etl,lightweight,pyspark,spark
Classifier: Intended Audience :: Developers
Classifier: Intended Audience :: Information Technology
Classifier: Intended Audience :: Science/Research
Classifier: License :: OSI Approved :: Apache Software License
Classifier: Operating System :: OS Independent
Classifier: Programming Language :: Python :: 3.10
Classifier: Programming Language :: Python :: 3.11
Classifier: Programming Language :: Python :: 3.12
Classifier: Topic :: Scientific/Engineering :: Information Analysis
Classifier: Topic :: Software Development :: Libraries
Classifier: Topic :: Software Development :: Quality Assurance
Requires-Python: >=3.10
Requires-Dist: pydantic<3.0.0,>=2.8.0
Provides-Extra: spark
Requires-Dist: pyspark<4.0.0,>=3.5.0; extra == 'spark'
